{
  "projects": [
    {
      "id": 1,
      "title": "Solar Power Station",
      "description": "Солнечная электростанция нового поколения",
      "capacity": "120 MW"
    },
    {
      "id": 2,
      "title": "Wind Energy Park",
      "description": "Ветровой парк в горной местности",
      "capacity": "200 MW"
    },
    {
      "id": 3,
      "title": "Hydro Power Plant",
      "description": "Гидроэлектростанция на горной реке",
      "capacity": "350 MW"
    }
  ],
  "news": [
    {
      "id": 1,
      "title": "Рост зелёной энергетики",
      "text": "Возобновляемые источники энергии показывают рекордный рост."
    },
    {
      "id": 2,
      "title": "Инвестиции в энергетику",
      "text": "Инвесторы активно вкладываются в солнечные проекты."
    }
  ]
}
